snips_nlu_metrics/__init__.py
snips_nlu_metrics/__version__
snips_nlu_metrics/engine.py
snips_nlu_metrics/metrics.py
snips_nlu_metrics/utils/__init__.py
snips_nlu_metrics/utils/constants.py
snips_nlu_metrics/utils/dataset_utils.py
snips_nlu_metrics/utils/exception.py
snips_nlu_metrics/utils/metrics_utils.py
snips_nlu_metrics/utils/temp_utils.py
snips_nlu_metrics-0.15.0.dist-info/AUTHORS.rst
snips_nlu_metrics-0.15.0.dist-info/LICENSE
snips_nlu_metrics-0.15.0.dist-info/METADATA
snips_nlu_metrics-0.15.0.dist-info/WHEEL
snips_nlu_metrics-0.15.0.dist-info/top_level.txt
snips_nlu_metrics-0.15.0.dist-info/RECORD
