Metadata-Version: 2.1
Name: snips-nlu-metrics
Version: 0.15.0
Summary: Python package to compute NLU metrics
Home-page: https://github.com/snipsco/snips-nlu-metrics
Author: Adrien Ball
Author-email: adrien.ball@snips.ai
License: Apache 2.0
Keywords: metrics nlu nlp intent slots entity parsing
Platform: UNKNOWN
Classifier: Programming Language :: Python :: 3
Classifier: Programming Language :: Python :: 3.5
Classifier: Programming Language :: Python :: 3.6
Classifier: Programming Language :: Python :: 3.7
Classifier: Programming Language :: Python :: 3.8
Requires-Dist: numpy (<2.0,>=1.7)
Requires-Dist: scipy (<2.0,>=1.0)
Requires-Dist: joblib (<0.15,>=0.13)
Requires-Dist: scikit-learn (<0.23,>=0.21.0) ; python_version >= "3.5"
Provides-Extra: test
Requires-Dist: mock (<3.0,>=2.0) ; extra == 'test'
Requires-Dist: pytest (<6,>=5.3.1) ; extra == 'test'
